iamai/__init__.py
iamai/adapter/__init__.py
iamai/adapter/apscheduler/__init__.py
iamai/adapter/apscheduler/config.py
iamai/adapter/apscheduler/event.py
iamai/adapter/cqhttp/__init__.py
iamai/adapter/cqhttp/config.py
iamai/adapter/cqhttp/event.py
iamai/adapter/cqhttp/exceptions.py
iamai/adapter/cqhttp/message.py
iamai/adapter/dingtalk/__init__.py
iamai/adapter/dingtalk/config.py
iamai/adapter/dingtalk/event.py
iamai/adapter/dingtalk/exceptions.py
iamai/adapter/dingtalk/message.py
iamai/adapter/http_server_test_adapter.py
iamai/adapter/mirai/__init__.py
iamai/adapter/mirai/config.py
iamai/adapter/mirai/event/__init__.py
iamai/adapter/mirai/event/base.py
iamai/adapter/mirai/event/mate.py
iamai/adapter/mirai/event/message.py
iamai/adapter/mirai/event/notice.py
iamai/adapter/mirai/event/request.py
iamai/adapter/mirai/exceptions.py
iamai/adapter/mirai/message.py
iamai/adapter/test.py
iamai/adapter/utils.py
iamai/bot.py
iamai/config.py
iamai/event.py
iamai/exceptions.py
iamai/log.py
iamai/message.py
iamai/plugin.py
iamai/py.typed
iamai/typing.py
iamai/utils.py
iamai-5.0.5.dist-info/LICENSE
iamai-5.0.5.dist-info/METADATA
iamai-5.0.5.dist-info/WHEEL
iamai-5.0.5.dist-info/RECORD
