Metadata-Version: 2.1
Name: iamai
Version: 5.0.5
Summary: bot framework.
Home-page: https://retrofor.space/
License: MIT
Keywords: bot,qq,qqbot,mirai,coolq
Author: 简律纯
Author-email: admin@jyunko.cn
Requires-Python: >=3.8,<4.0
Classifier: Development Status :: 5 - Production/Stable
Classifier: Framework :: Robot Framework
Classifier: Framework :: Robot Framework :: Library
Classifier: License :: OSI Approved :: MIT License
Classifier: Operating System :: OS Independent
Classifier: Programming Language :: Python :: 3
Classifier: Programming Language :: Python :: 3.8
Classifier: Programming Language :: Python :: 3.9
Classifier: Programming Language :: Python :: 3.10
Classifier: Programming Language :: Python :: 3.11
Classifier: Programming Language :: Python :: 3
Provides-Extra: aiohttp
Provides-Extra: all
Provides-Extra: fastapi
Provides-Extra: httpx
Provides-Extra: quart
Provides-Extra: websockets
Requires-Dist: Quart (>=0.18.0,<1.0.0) ; extra == "quart" or extra == "all"
Requires-Dist: aiohttp[speedups] (>=3.7.4,<4.0.0) ; extra == "aiohttp" or extra == "all"
Requires-Dist: fastapi (>=0.87.0,!=0.89.0,<1.0.0) ; extra == "fastapi" or extra == "all"
Requires-Dist: httpx[http2] (>=0.20.0,<1.0.0) ; extra == "httpx" or extra == "all"
Requires-Dist: loguru (>=0.6.0,<0.7.0)
Requires-Dist: pydantic[dotenv] (>=1.10.0,<2.0.0)
Requires-Dist: pygtrie (>=2.4.1,<3.0.0)
Requires-Dist: tomlkit (>=0.10.0,<1.0.0)
Requires-Dist: typing-extensions (>=3.10.0,<5.0.0)
Requires-Dist: uvicorn[standard] (>=0.20.0,<1.0.0) ; extra == "quart" or extra == "fastapi" or extra == "all"
Requires-Dist: websockets (>=10.0,<11.0) ; extra == "websockets" or extra == "all"
Requires-Dist: yarl (>=1.7.2,<2.0.0)
Project-URL: Documentation, https://iamai.retrofor.space/
Project-URL: Repository, https://github.com/retrofor/iamai
